jaraco/media/__init__.py
jaraco/media/arguments.py
jaraco/media/concat.py
jaraco/media/config.py
jaraco/media/cropdetect.py
jaraco/media/dvd.py
jaraco/media/dvd_info.py
jaraco/media/handbrake.py
jaraco/media/index.py
jaraco/media/isapiapp.py
jaraco/media/matroska.py
jaraco/media/splice.py
jaraco/media/srt-concat.py
jaraco/media/srt.py
jaraco/media/tests/__init__.py
jaraco/media/tests/multi title output.txt
jaraco/media/tests/test_handbrake.py
jaraco.media-4.0.1.dist-info/LICENSE
jaraco.media-4.0.1.dist-info/METADATA
jaraco.media-4.0.1.dist-info/WHEEL
jaraco.media-4.0.1.dist-info/entry_points.txt
jaraco.media-4.0.1.dist-info/top_level.txt
jaraco.media-4.0.1.dist-info/RECORD
