Metadata-Version: 2.1
Name: jaraco.media
Version: 4.0.1
Summary: DVD and other multimedia tools
Author-email: "Jason R. Coombs" <jaraco@jaraco.com>
Project-URL: Homepage, https://github.com/jaraco/jaraco.media
Classifier: Development Status :: 5 - Production/Stable
Classifier: Intended Audience :: Developers
Classifier: License :: OSI Approved :: MIT License
Classifier: Programming Language :: Python :: 3
Classifier: Programming Language :: Python :: 3 :: Only
Requires-Python: >=3.8
License-File: LICENSE
Requires-Dist: jaraco.text >=3.4
Requires-Dist: jaraco.ui
Requires-Dist: jaraco.context
Requires-Dist: jaraco.path >=3.1
Requires-Dist: jaraco.functools
Requires-Dist: jaraco.itertools >=6.2
Requires-Dist: httpagentparser
Requires-Dist: more-itertools
Requires-Dist: path
Requires-Dist: inflect
Requires-Dist: autocommand
Requires-Dist: tempora
Requires-Dist: jaraco.packaging >=10.1
Requires-Dist: importlib-metadata ; python_version < "3.8"
Provides-Extra: docs
Requires-Dist: sphinx >=3.5 ; extra == 'docs'
Requires-Dist: jaraco.packaging >=9.3 ; extra == 'docs'
Requires-Dist: rst.linker >=1.9 ; extra == 'docs'
Requires-Dist: furo ; extra == 'docs'
Requires-Dist: sphinx-lint ; extra == 'docs'
Provides-Extra: testing
Requires-Dist: pytest !=8.1.*,>=6 ; extra == 'testing'
Requires-Dist: pytest-checkdocs >=2.4 ; extra == 'testing'
Requires-Dist: pytest-cov ; extra == 'testing'
Requires-Dist: pytest-mypy ; extra == 'testing'
Requires-Dist: pytest-enabler >=2.2 ; extra == 'testing'
Requires-Dist: pytest-ruff >=0.2.1 ; extra == 'testing'
Requires-Dist: cherrypy ; extra == 'testing'
Requires-Dist: genshi ; extra == 'testing'
Requires-Dist: importlib-resources ; extra == 'testing'
